README.md
setup.cfg
setup.py
Starlette_WTF.egg-info/PKG-INFO
Starlette_WTF.egg-info/SOURCES.txt
Starlette_WTF.egg-info/dependency_links.txt
Starlette_WTF.egg-info/not-zip-safe
Starlette_WTF.egg-info/requires.txt
Starlette_WTF.egg-info/top_level.txt
starlette_wtf/__init__.py
starlette_wtf/csrf.py
starlette_wtf/form.py
starlette_wtf/util.py